Topsis_Himanshu_102103568/__init__.py
Topsis_Himanshu_102103568/topsis.py
Topsis_Himanshu_102103568-1.0.3.dist-info/LICENSE
Topsis_Himanshu_102103568-1.0.3.dist-info/METADATA
Topsis_Himanshu_102103568-1.0.3.dist-info/WHEEL
Topsis_Himanshu_102103568-1.0.3.dist-info/top_level.txt
Topsis_Himanshu_102103568-1.0.3.dist-info/RECORD
