Metadata-Version: 2.1
Name: Topsis-Himanshu-102103568
Version: 1.0.3
Summary: Implementation of Topsis
Author: Himanshu Bansal
Author-email: himu90505@gmail.com
License: MIT License
Project-URL: Project Link, https://github.com/himu23369/Topsis-Himanshu-102103568
Keywords: Topsis,Topsis-Himanshu-102103568,Himanshu,Topsis-Himanshu,102103568
Classifier: Development Status :: 3 - Alpha
Classifier: License :: OSI Approved :: MIT License
Classifier: Operating System :: OS Independent
Classifier: Intended Audience :: Developers
Classifier: Programming Language :: Python :: 3
License-File: LICENSE
Requires-Dist: pandas
Requires-Dist: numpy
